pfshelper/__init__.py
pfshelper/experimental/__init__.py
pfshelper/experimental/splitters.py
pfshelper/experimental/transformers.py
pfshelper-0.0.7.dist-info/LICENSE
pfshelper-0.0.7.dist-info/METADATA
pfshelper-0.0.7.dist-info/WHEEL
pfshelper-0.0.7.dist-info/top_level.txt
pfshelper-0.0.7.dist-info/RECORD
