Metadata-Version: 2.1
Name: pfshelper
Version: 0.0.7
Summary: A humble helper for time series panel data
Home-page: https://github.com/coffepowered/pfs-helper/
Author: Andrea
Author-email: nescio.adv@gmail.com
License: UNKNOWN
Project-URL: Bug Tracker, https://github.com/coffepowered/pfs-helper/labels/bug
Platform: UNKNOWN
Classifier: Programming Language :: Python :: 3
Classifier: License :: OSI Approved :: MIT License
Classifier: Operating System :: OS Independent
Requires-Python: >=3.7
License-File: LICENSE
